setup.py
medal/__init__.py
medal.egg-info/PKG-INFO
medal.egg-info/SOURCES.txt
medal.egg-info/dependency_links.txt
medal.egg-info/top_level.txt