Metadata-Version: 1.0
Name: medal
Version: 0.0.0
Summary: A Medal API wrapper for modern Python 3
Home-page: UNKNOWN
Author: Zenqi
Author-email: UNKNOWN
License: MIT
Platform: UNKNOWN
